claude_force/__init__.py
claude_force/__main__.py
claude_force/agent_memory.py
claude_force/agent_router.py
claude_force/analytics.py
claude_force/async_orchestrator.py
claude_force/base.py
claude_force/cli.py
claude_force/constants.py
claude_force/contribution.py
claude_force/demo_mode.py
claude_force/diagnostics.py
claude_force/error_helpers.py
claude_force/hybrid_orchestrator.py
claude_force/import_export.py
claude_force/marketplace.py
claude_force/mcp_server.py
claude_force/orchestrator.py
claude_force/path_validator.py
claude_force/performance_tracker.py
claude_force/quick_start.py
claude_force/response_cache.py
claude_force/semantic_selector.py
claude_force/skills_manager.py
claude_force/template_gallery.py
claude_force/workflow_composer.py
claude_force/models/__init__.py
claude_force/models/handoff.py
claude_force/models/meta_prompt.py
claude_force/models/todo.py
claude_force/services/__init__.py
claude_force/services/handoff_generator.py
claude_force/services/meta_prompter.py
claude_force/services/todo_manager.py
claude_force/templates/agents/ai-engineer.md
claude_force/templates/agents/api-documenter.md
claude_force/templates/agents/backend-architect.md
claude_force/templates/agents/bug-investigator.md
claude_force/templates/agents/claude-code-expert.md
claude_force/templates/agents/code-reviewer.md
claude_force/templates/agents/crypto-data-engineer.md
claude_force/templates/agents/crypto-security-auditor.md
claude_force/templates/agents/crypto-trading-architect.md
claude_force/templates/agents/data-engineer.md
claude_force/templates/agents/database-architect.md
claude_force/templates/agents/deployment-integration-expert.md
claude_force/templates/agents/devops-architect.md
claude_force/templates/agents/document-writer-expert.md
claude_force/templates/agents/exchange-integration-specialist.md
claude_force/templates/agents/execution-optimization-expert.md
claude_force/templates/agents/frontend-architect.md
claude_force/templates/agents/frontend-developer.md
claude_force-1.1.0.dist-info/METADATA
claude_force-1.1.0.dist-info/WHEEL
claude_force-1.1.0.dist-info/entry_points.txt
claude_force-1.1.0.dist-info/top_level.txt
claude_force-1.1.0.dist-info/RECORD
