Metadata-Version: 2.4
Name: claude-force
Version: 1.1.0
Summary: Multi-Agent Orchestration System for Claude
Home-page: https://github.com/khanh-vu/claude-force
Author: Claude Force Team
Author-email: 
License: MIT
Project-URL: Homepage, https://github.com/khanh-vu/claude-force
Project-URL: Documentation, https://github.com/khanh-vu/claude-force/blob/main/README.md
Project-URL: Repository, https://github.com/khanh-vu/claude-force
Project-URL: Issues, https://github.com/khanh-vu/claude-force/issues
Keywords: claude,anthropic,ai,agents,multi-agent,orchestration
Classifier: Development Status :: 4 - Beta
Classifier: Intended Audience :: Developers
Classifier: Topic :: Software Development :: Libraries :: Application Frameworks
Classifier: License :: OSI Approved :: MIT License
Classifier: Programming Language :: Python :: 3
Classifier: Programming Language :: Python :: 3.8
Classifier: Programming Language :: Python :: 3.9
Classifier: Programming Language :: Python :: 3.10
Classifier: Programming Language :: Python :: 3.11
Classifier: Programming Language :: Python :: 3.12
Requires-Python: >=3.8
Requires-Dist: anthropic>=0.40.0
Requires-Dist: PyYAML>=6.0.0
Provides-Extra: dev
Requires-Dist: pytest>=8.0.0; extra == "dev"
Requires-Dist: pytest-cov>=4.1.0; extra == "dev"
Requires-Dist: pytest-asyncio>=0.23.0; extra == "dev"
Requires-Dist: black>=24.0.0; extra == "dev"
Requires-Dist: pylint>=3.0.0; extra == "dev"
Requires-Dist: mypy>=1.8.0; extra == "dev"
Requires-Dist: tenacity>=8.0.0; extra == "dev"
Requires-Dist: aiofiles>=23.0.0; extra == "dev"
Dynamic: home-page
Dynamic: requires-python
